flask_yookassa.py
Flask_Yookassa-0.1.0.dist-info/LICENSE
Flask_Yookassa-0.1.0.dist-info/METADATA
Flask_Yookassa-0.1.0.dist-info/WHEEL
Flask_Yookassa-0.1.0.dist-info/top_level.txt
Flask_Yookassa-0.1.0.dist-info/RECORD
