Metadata-Version: 2.1
Name: Flask-Yookassa
Version: 0.1.0
Summary: Integration of Flask and YuKassa.
Author-email: Kirill Vercetti <office@kyzima-spb.com>
License: MIT License
Project-URL: Homepage, https://github.com/kyzima-spb/flask-yookassa/
Project-URL: Repository, https://github.com/kyzima-spb/flask-yookassa.git
Project-URL: Bug Tracker, https://github.com/kyzima-spb/flask-yookassa/issues/
Classifier: Environment :: Web Environment
Classifier: Intended Audience :: Developers
Classifier: Operating System :: OS Independent
Classifier: Programming Language :: Python
Classifier: Framework :: Flask
Classifier: Development Status :: 3 - Alpha
Classifier: Topic :: Internet :: WWW/HTTP
Classifier: Topic :: Internet :: WWW/HTTP :: Dynamic Content
Requires-Python: >=3.7
License-File: LICENSE
Requires-Dist: Flask (>=1.0)
Requires-Dist: yookassa (>=2)
Provides-Extra: dev
Requires-Dist: mypy ; extra == 'dev'
